CHANGELOG.rst
MANIFEST.in
README.rst
setup.py
./CHANGELOG.rst
./README.rst
./build/lib/tos/dlg/act01/edward.rst
./build/lib/tos/dlg/act01/enter.rst
./build/lib/tos/dlg/act01/foyer.rst
./build/lib/tos/dlg/act01/pause.rst
./build/lib/tos/dlg/act01/quit.rst
./build/lib/tos/dlg/act01/room.rst
./build/lib/tos/dlg/act03/improvise.rst
./build/lib/tos/dlg/act03/message.rst
./build/lib/tos/dlg/act03/news.rst
./build/lib/tos/dlg/act03/office.rst
./build/lib/tos/dlg/act03/pause.rst
./build/lib/tos/dlg/act03/quit.rst
./build/lib/tos/dlg/act03/room.rst
./build/lib/tos/dlg/act03/rump.rst
./build/lib/tos/web/titles.html
./build/lib/tos/web/css/tos.css
./tos/dlg/act01/edward.rst
./tos/dlg/act01/enter.rst
./tos/dlg/act01/foyer.rst
./tos/dlg/act01/pause.rst
./tos/dlg/act01/quit.rst
./tos/dlg/act01/room.rst
./tos/dlg/act03/improvise.rst
./tos/dlg/act03/message.rst
./tos/dlg/act03/news.rst
./tos/dlg/act03/office.rst
./tos/dlg/act03/pause.rst
./tos/dlg/act03/quit.rst
./tos/dlg/act03/room.rst
./tos/dlg/act03/rump.rst
./tos/web/titles.html
./tos/web/css/tos.css
theatre_of_spud.egg-info/PKG-INFO
theatre_of_spud.egg-info/SOURCES.txt
theatre_of_spud.egg-info/dependency_links.txt
theatre_of_spud.egg-info/entry_points.txt
theatre_of_spud.egg-info/requires.txt
theatre_of_spud.egg-info/top_level.txt
theatre_of_spud.egg-info/zip-safe
tos/__init__.py
tos/acts.py
tos/app.py
tos/calls.py
tos/knowledge.py
tos/lights.py
tos/main.py
tos/map.py
tos/story.py
tos/types.py
tos/dlg/__init__.py
tos/dlg/act01/__init__.py
tos/dlg/act01/edward.rst
tos/dlg/act01/enter.rst
tos/dlg/act01/foyer.rst
tos/dlg/act01/pause.rst
tos/dlg/act01/quit.rst
tos/dlg/act01/room.rst
tos/dlg/act03/__init__.py
tos/dlg/act03/improvise.rst
tos/dlg/act03/message.rst
tos/dlg/act03/news.rst
tos/dlg/act03/office.rst
tos/dlg/act03/pause.rst
tos/dlg/act03/quit.rst
tos/dlg/act03/room.rst
tos/dlg/act03/rump.rst
tos/mixins/__init__.py
tos/mixins/carrying.py
tos/mixins/directing.py
tos/mixins/helpful.py
tos/mixins/moving.py
tos/mixins/navigator.py
tos/mixins/patrolling.py
tos/mixins/telegraph.py
tos/mixins/types.py
tos/mixins/test/__init__.py
tos/mixins/test/test_carrying.py
tos/mixins/test/test_directing.py
tos/mixins/test/test_helpful.py
tos/mixins/test/test_moving.py
tos/mixins/test/test_patrolling.py
