Metadata-Version: 2.1
Name: theatre-of-spud
Version: 0.6.0
Summary: A text-driven web game.
Home-page: https://github.com/tundish/theatre_of_spud
Author: D E Haynes
Author-email: tundish@gigeconomy.org.uk
License: UNKNOWN
Platform: UNKNOWN
Classifier: Operating System :: OS Independent
Classifier: Programming Language :: Python :: 3.7
Classifier: Programming Language :: Python :: 3.8
Classifier: Programming Language :: Python :: 3.9
Classifier: License :: OSI Approved :: GNU Affero General Public License v3 or later (AGPLv3+)
Provides-Extra: dev
